crelm/__init__.py
crelm/factory.py
crelm/libcrelm.py
crelm/makeheaders.c
crelm/makeheaders_crelm.c
crelm/tube.py
crelm-0.0.36.dist-info/LICENSE
crelm-0.0.36.dist-info/METADATA
crelm-0.0.36.dist-info/WHEEL
crelm-0.0.36.dist-info/RECORD
